setup.cfg
setup.py
ftransc_gui/__init__.py
ftransc_gui/constants.py
ftransc_gui/gui.py
ftransc_gui/launcher.py
ftransc_gui/utils.py
ftransc_gui.egg-info/PKG-INFO
ftransc_gui.egg-info/SOURCES.txt
ftransc_gui.egg-info/dependency_links.txt
ftransc_gui.egg-info/entry_points.txt
ftransc_gui.egg-info/requires.txt
ftransc_gui.egg-info/top_level.txt