Metadata-Version: 1.1
Name: ftransc-gui
Version: 1.0.5
Summary: The GUI application for ftransc
Home-page: https://github.com/dopstar/ftransc-gui
Author: Mkhanyisi Madlavana
Author-email: mkhanyisi@gmail.com
License: UNKNOWN
Download-URL: https://github.com/dopstar/ftransc-gui/tarball/1.0.5
Keywords: ftransc,gui,audio,convert,ffmpeg,avconv,mp3,wma,ogg,flac,transcode,qt
Platform: UNKNOWN
Classifier: Development Status :: 5 - Production/Stable
Classifier: Intended Audience :: End Users/Desktop
Classifier: Natural Language :: English
Classifier: Programming Language :: Python :: 3.6
